[
{"name":"Abacus","vhb_2024":"B","areas":["Accounting","Finance"]},
{"name":"Academy of Management Annals","vhb_2024":"A","areas":["Int. Management","Logistik","Management","Marketing","Nachhaltigkeit","OR","Org","Personal","TIE","WI","Wissenschaftstheorie"]},
{"name":"Academy of Management Discoveries","vhb_2024":"A","areas":["Logistik","Management","Nachhaltigkeit","Org","Personal","TIE","WI"]},
{"name":"Academy of Management Journal","vhb_2024":"A+","areas":["Accounting","Dienstleistung","Int. Management","Logistik","Management","Marketing","Nachhaltigkeit","OR","Org","Personal","TIE","WI","Wissenschaftstheorie"]},
{"name":"Academy of Management Learning &amp; Education","vhb_2024":"B","areas":["Hochschulmanagement","Logistik","Nachhaltigkeit","Org","Personal","TIE","WI"]},
{"name":"Academy of Management Perspectives","vhb_2024":"A","areas":["Int. Management","Logistik","Management","Marketing","Nachhaltigkeit","OR","Org","Personal","TIE","WI","Wissenschaftstheorie"]},
{"name":"Academy of Management Review","vhb_2024":"A+","areas":["Accounting","Dienstleistung","Int. Management","Logistik","Management","Marketing","Nachhaltigkeit","OR","Org","Personal","TIE","WI","Wissenschaftstheorie"]},
{"name":"Accounting and Business Research","vhb_2024":"B","areas":["Accounting","Steuern"]},
{"name":"Accounting and Finance","vhb_2024":"B","areas":["Accounting","Finance"]},
{"name":"Accounting and the Public Interest","vhb_2024":"B","areas":["Accounting"]},
{"name":"Accounting Education: An International Journal","vhb_2024":"B","areas":["Accounting"]},
{"name":"Accounting Forum","vhb_2024":"B","areas":["Accounting"]},
{"name":"Accounting Historians Journal","vhb_2024":"B","areas":["Accounting"]},
{"name":"Accounting History","vhb_2024":"B","areas":["Accounting"]},
{"name":"Accounting History Review","vhb_2024":"B","areas":["Accounting"]},
{"name":"Accounting Horizons","vhb_2024":"B","areas":["Accounting","Steuern"]},
{"name":"Accounting in Europe","vhb_2024":"B","areas":["Accounting"]},
{"name":"Accounting Perspectives","vhb_2024":"B","areas":["Accounting"]},
{"name":"Accounting Review","vhb_2024":"A+","areas":["Accounting","Finance","Steuern"]},
{"name":"Accounting, Auditing &amp; Accountability Journal","vhb_2024":"A","areas":["Accounting","Nachhaltigkeit"]},
{"name":"Accounting, Economics, and Law - A Convivium","vhb_2024":"B","areas":["Accounting"]},
{"name":"Accounting, Organizations and Society","vhb_2024":"A+","areas":["Accounting","Finance","Nachhaltigkeit","Org","Steuern","TIE"]},
{"name":"ACM Computing Surveys","vhb_2024":"A","areas":["WI"]},
{"name":"Administration &amp; Society","vhb_2024":"B","areas":["Öffentliche BWL"]},
{"name":"Administrative Science Quarterly","vhb_2024":"A+","areas":["Accounting","Dienstleistung","Int. Management","Management","Marketing","Nachhaltigkeit","OR","Org","Personal","TIE","WI","Wissenschaftstheorie"]},
{"name":"Advances in Accounting","vhb_2024":"B","areas":["Accounting"]},
{"name":"Advances in Accounting Behavioral Research","vhb_2024":"B","areas":["Accounting"]},
{"name":"Advances in Strategic Management","vhb_2024":"B","areas":["Int. Management","Management","Org"]},
{"name":"Advances of Applied Energy","vhb_2024":"B","areas":["Nachhaltigkeit"]},
{"name":"American Economic Journal: Applied Economics","vhb_2024":"A","areas":["Finance"]},
{"name":"American Economic Journal: Economic Policy","vhb_2024":"A","areas":["Finance","Steuern"]},
{"name":"American Economic Journal: Macroeconomics","vhb_2024":"A","areas":["Finance"]},
{"name":"American Economic Journal: Microeconomics","vhb_2024":"A","areas":["Finance"]},
{"name":"American Economic Review","vhb_2024":"A+","areas":["Finance","Int. Management","Marketing","OR","Wissenschaftstheorie"]},
{"name":"American Economic Review: Insights","vhb_2024":"A","areas":["Finance"]},
{"name":"American Journal of Health Economics","vhb_2024":"B","areas":["Öffentliche BWL"]},
{"name":"AMS Review","vhb_2024":"B","areas":["Dienstleistung","Marketing"]},
{"name":"Annual Review of Financial Economics","vhb_2024":"B","areas":["Finance"]},
{"name":"Annual Review of Organizational Psychology and Organizational Behavior","vhb_2024":"A","areas":["Org","Personal"]},
{"name":"Appetite","vhb_2024":"B","areas":["Marketing"]},
{"name":"Applied Energy","vhb_2024":"B","areas":["Nachhaltigkeit","WI"]},
{"name":"Applied Health Economics and Health Policy","vhb_2024":"B","areas":["Öffentliche BWL"]},
{"name":"Applied Mathematical Modelling","vhb_2024":"B","areas":["Logistik","OR","Produktion"]},
{"name":"Applied Psychology: An International Review","vhb_2024":"B","areas":["Int. Management","Org","Personal"]},
{"name":"Asia Pacific Journal of Management","vhb_2024":"B","areas":["Personal"]},
{"name":"Auditing: A Journal of Practice &amp; Theory","vhb_2024":"A","areas":["Accounting"]},
{"name":"Australian Accounting Review","vhb_2024":"B","areas":["Accounting"]},
{"name":"BB-Betriebs-Berater","vhb_2024":"B","areas":["Steuern"]},
{"name":"Behavior Research Methods","vhb_2024":"B","areas":["Marketing"]},
{"name":"Behavioral Public Policy","vhb_2024":"B","areas":["Öffentliche BWL"]},
{"name":"Behavioral Research in Accounting","vhb_2024":"B","areas":["Accounting","Steuern"]},
{"name":"Betriebswirtschaftliche Forschung und Praxis (BFuP)","vhb_2024":"A","areas":["Steuern"]},
{"name":"Big Data &amp; Society","vhb_2024":"B","areas":["Org"]},
{"name":"Biomass and Bioenergy","vhb_2024":"B","areas":["Nachhaltigkeit"]},
{"name":"British Food Journal","vhb_2024":"B","areas":["Marketing"]},
{"name":"British Journal of Industrial Relations","vhb_2024":"A","areas":["Int. Management","Org","Personal"]},
{"name":"British Journal of Management","vhb_2024":"B","areas":["Accounting","Dienstleistung","Int. Management","Management","Marketing","Nachhaltigkeit","Org","Personal","TIE","Wissenschaftstheorie"]},
{"name":"British Tax Review","vhb_2024":"B","areas":["Steuern"]},
{"name":"Business &amp; Society","vhb_2024":"A","areas":["Accounting","Management","Nachhaltigkeit","Org","Personal","Wissenschaftstheorie","Öffentliche BWL"]},
{"name":"Business and Society Review","vhb_2024":"B","areas":["Nachhaltigkeit","Wissenschaftstheorie"]},
{"name":"Business Ethics Quarterly","vhb_2024":"A","areas":["Accounting","Management","Nachhaltigkeit","Org","Personal","Wissenschaftstheorie"]},
{"name":"Business Ethics, the Environment &amp; Responsibility","vhb_2024":"B","areas":["Wissenschaftstheorie"]},
{"name":"Business Ethics: A European Review","vhb_2024":"B","areas":["Accounting","Nachhaltigkeit"]},
{"name":"Business Horizons","vhb_2024":"B","areas":["Org"]},
{"name":"Business Research","vhb_2024":"B","areas":["Finance","Logistik","Org","Personal","Wissenschaftstheorie"]},
{"name":"Business Research Quarterly","vhb_2024":"B","areas":["Personal"]},
{"name":"Business Strategy and Development","vhb_2024":"B","areas":["Nachhaltigkeit"]},
{"name":"Business Strategy and the Environment","vhb_2024":"B","areas":["Accounting","Management","Marketing","Nachhaltigkeit","Org"]},
{"name":"California Management Review","vhb_2024":"B","areas":["Accounting","Dienstleistung","Int. Management","Logistik","Management","Marketing","Nachhaltigkeit","OR","Org","Personal","Produktion","TIE","WI","Wissenschaftstheorie"]},
{"name":"Canadian Journal of Economics","vhb_2024":"B","areas":["Steuern"]},
{"name":"Computational Management Science","vhb_2024":"B","areas":["OR"]},
{"name":"Computers &amp; Chemical Engineering","vhb_2024":"B","areas":["Produktion"]},
{"name":"Computers &amp; Security","vhb_2024":"B","areas":["WI"]},
{"name":"Computers and Industrial Engineering","vhb_2024":"B","areas":["Dienstleistung","Logistik","OR","Produktion"]},
{"name":"Contemporary Accounting Research","vhb_2024":"A+","areas":["Accounting","Finance","Steuern"]},
{"name":"Corporate Governance: An International Review","vhb_2024":"B","areas":["Accounting","Int. Management","Management","Org","Wissenschaftstheorie"]},
{"name":"Corporate Social Responsibility and Environmental Management","vhb_2024":"B","areas":["Nachhaltigkeit"]},
{"name":"Creativity and Innovation Management","vhb_2024":"B","areas":["Dienstleistung","Org","Personal","TIE"]},
{"name":"Critical Finance Review","vhb_2024":"A","areas":["Finance"]},
{"name":"Critical Perspectives on Accounting","vhb_2024":"B","areas":["Accounting"]},
{"name":"Cross Cultural &amp; Strategic Management","vhb_2024":"B","areas":["Int. Management"]},
{"name":"Culture and Organization","vhb_2024":"B","areas":["Org","Personal"]},
{"name":"DBW Die Betriebswirtschaft - Business Administration Review","vhb_2024":"B","areas":["Org"]},
{"name":"Decision Analysis","vhb_2024":"B","areas":["OR"]},
{"name":"Der Betrieb","vhb_2024":"B","areas":["Steuern"]},
{"name":"Deutsches Steuerrecht (DStR)","vhb_2024":"B","areas":["Steuern"]},
{"name":"Die Unternehmensbesteuerung (Ubg)","vhb_2024":"B","areas":["Steuern"]},
{"name":"Die Wirtschaftsprüfung (WPg)","vhb_2024":"B","areas":["Steuern"]},
{"name":"Discrete Applied Mathematics","vhb_2024":"A","areas":["Logistik","OR","Produktion"]},
{"name":"Ecological Economics","vhb_2024":"B","areas":["Nachhaltigkeit"]},
{"name":"Econometrica","vhb_2024":"A+","areas":["Finance","Int. Management","Marketing","OR"]},
{"name":"Economic and Industrial Democracy","vhb_2024":"B","areas":["Personal"]},
{"name":"Economics Letters","vhb_2024":"B","areas":["Finance","Personal","Steuern","WI"]},
{"name":"Employee Relations","vhb_2024":"B","areas":["Org","Personal"]},
{"name":"Energy","vhb_2024":"B","areas":["OR","WI"]},
{"name":"Energy Economics","vhb_2024":"B","areas":["Nachhaltigkeit","OR","TIE"]},
{"name":"Energy Policy","vhb_2024":"B","areas":["Logistik","Nachhaltigkeit","OR","TIE","Öffentliche BWL"]},
{"name":"Energy Research and Social Science","vhb_2024":"B","areas":["Nachhaltigkeit"]},
{"name":"Energy Strategy Reviews","vhb_2024":"B","areas":["Nachhaltigkeit"]},
{"name":"Entrepreneurship and Regional Development","vhb_2024":"B","areas":["Management","Org","TIE"]},
{"name":"Entrepreneurship, Theory and Practice","vhb_2024":"A","areas":["Management","Org","TIE"]},
{"name":"Environmental Science and Technology","vhb_2024":"B","areas":["Nachhaltigkeit"]},
{"name":"Equality, Diversity and Inclusion: An International Journal","vhb_2024":"B","areas":["Org","Personal"]},
{"name":"EURO Journal on Computational Optimization","vhb_2024":"B","areas":["Logistik","OR","Produktion"]},
{"name":"EURO Journal on Decision Processes","vhb_2024":"B","areas":["Logistik","OR"]},
{"name":"EURO Journal on Transportation and Logistics","vhb_2024":"B","areas":["Logistik","OR","Produktion"]},
{"name":"European Accounting Review","vhb_2024":"A","areas":["Accounting","Finance","Steuern"]},
{"name":"European Business Review","vhb_2024":"B","areas":["Management","Org"]},
{"name":"European Economic Review","vhb_2024":"A","areas":["Finance","Steuern"]},
{"name":"European Financial Management","vhb_2024":"B","areas":["Finance"]},
{"name":"European Journal of Finance","vhb_2024":"B","areas":["Accounting","Finance"]},
{"name":"European Journal of Industrial Relations","vhb_2024":"B","areas":["Org","Personal"]},
{"name":"European Journal of International Management","vhb_2024":"B","areas":["Int. Management","Management","Org","Personal"]},
{"name":"European Journal of Law and Economics","vhb_2024":"B","areas":["Steuern"]},
{"name":"European Journal of Management","vhb_2024":"B","areas":["Int. Management","Marketing","Nachhaltigkeit","Personal"]},
{"name":"European Journal of Marketing","vhb_2024":"B","areas":["Dienstleistung","Marketing"]},
{"name":"European Journal of Work and Organizational Psychology","vhb_2024":"B","areas":["Org","Personal"]},
{"name":"European Management Journal","vhb_2024":"B","areas":["Accounting","Dienstleistung","Int. Management","Management","Marketing","Nachhaltigkeit","Org","Personal","TIE","WI","Wissenschaftstheorie"]},
{"name":"European Management Review","vhb_2024":"B","areas":["Accounting","Int. Management","Management","Org","Personal","TIE","Wissenschaftstheorie"]},
{"name":"Family Business Review","vhb_2024":"B","areas":["Accounting","Management","Org","Personal","TIE"]},
{"name":"Finance and Stochastics","vhb_2024":"B","areas":["Finance"]},
{"name":"Finance Research Letters","vhb_2024":"B","areas":["Finance"]},
{"name":"Financial Accountability &amp; Management","vhb_2024":"B","areas":["Öffentliche BWL"]},
{"name":"Financial Analysts Journal","vhb_2024":"B","areas":["Accounting","Finance"]},
{"name":"Financial Management","vhb_2024":"B","areas":["Finance"]},
{"name":"Financial Markets and Portfolio Management","vhb_2024":"B","areas":["Finance"]},
{"name":"Financial Markets, Institutions and Instruments","vhb_2024":"B","areas":["Finance"]},
{"name":"Financial Review","vhb_2024":"B","areas":["Finance"]},
{"name":"Finanz-Rundschau","vhb_2024":"B","areas":["Steuern"]},
{"name":"FinanzArchiv - Public Finance Analysis","vhb_2024":"B","areas":["Steuern"]},
{"name":"Flexible Services and Manufacturing Journal","vhb_2024":"B","areas":["Dienstleistung","Logistik","OR","Produktion"]},
{"name":"Food Quality and Preferences","vhb_2024":"B","areas":["Marketing"]},
{"name":"Foundations and Trends in Accounting","vhb_2024":"B","areas":["Accounting"]},
{"name":"Fuzzy Sets and Systems","vhb_2024":"B","areas":["OR"]},
{"name":"Gender &amp; Society","vhb_2024":"B","areas":["Org","Personal"]},
{"name":"Gender, Work &amp; Organization","vhb_2024":"B","areas":["Org","Personal"]},
{"name":"Geneva Papers on Risk and Insurance: Issues and Practice","vhb_2024":"B","areas":["Finance"]},
{"name":"German Economic Review","vhb_2024":"B","areas":["Personal","Steuern"]},
{"name":"German Journal of Human Resource Management","vhb_2024":"B","areas":["Org","Personal"]},
{"name":"Global Strategy Journal","vhb_2024":"A","areas":["Int. Management","Management","Org"]},
{"name":"GmbH-Rundschau","vhb_2024":"B","areas":["Steuern"]},
{"name":"Governance","vhb_2024":"A","areas":["Öffentliche BWL"]},
{"name":"Group &amp; Organization Management","vhb_2024":"B","areas":["Management","Org","Personal"]},
{"name":"Group Processes &amp; Intergroup Relations","vhb_2024":"B","areas":["Personal"]},
{"name":"Harvard Business Review","vhb_2024":"B","areas":["Int. Management","Management","Marketing","Nachhaltigkeit","OR","Org","Personal","TIE","WI","Wissenschaftstheorie"]},
{"name":"Health Affairs","vhb_2024":"A","areas":["Öffentliche BWL"]},
{"name":"Health Care Management Review","vhb_2024":"B","areas":["Öffentliche BWL"]},
{"name":"Health Care Management Science","vhb_2024":"A","areas":["Logistik","OR","Produktion","WI","Öffentliche BWL"]},
{"name":"Health Economics","vhb_2024":"A","areas":["Öffentliche BWL"]},
{"name":"Health Economics, Policy and Law","vhb_2024":"B","areas":["Öffentliche BWL"]},
{"name":"Health Policy","vhb_2024":"B","areas":["Öffentliche BWL"]},
{"name":"Health Services Research","vhb_2024":"A","areas":["Öffentliche BWL"]},
{"name":"Higher Education Quarterly","vhb_2024":"B","areas":["Hochschulmanagement"]},
{"name":"Higher Education","vhb_2024":"A","areas":["Hochschulmanagement"]},
{"name":"Human Factors","vhb_2024":"B","areas":["Produktion"]},
{"name":"Human Relations","vhb_2024":"A","areas":["Management","Org","Personal","TIE"]},
{"name":"Human Resource Management","vhb_2024":"A","areas":["Org","Personal","TIE"]},
{"name":"Human Resource Management Journal","vhb_2024":"A","areas":["Org","Personal"]},
{"name":"Human Resource Management Review","vhb_2024":"A","areas":["Org","Personal"]},
{"name":"IEEE Engineering Management Review","vhb_2024":"B","areas":["Produktion","TIE","WI"]},
{"name":"IEEE Internet Computing","vhb_2024":"B","areas":["WI"]},
{"name":"IEEE Transactions on Intelligent Transportation Systems","vhb_2024":"B","areas":["Logistik"]},
{"name":"IISE Transactions","vhb_2024":"A","areas":["Dienstleistung","Logistik","OR","Produktion"]},
{"name":"ILR Review","vhb_2024":"A","areas":["Int. Management","Org","Personal","TIE"]},
{"name":"IMA Journal of Management Mathematics","vhb_2024":"B","areas":["Logistik","OR","Produktion"]},
{"name":"Industrial and Corporate Change","vhb_2024":"B","areas":["Dienstleistung","Management","Org","TIE"]},
{"name":"Industrial Marketing Management","vhb_2024":"B","areas":["Dienstleistung","Management","Marketing","Org","TIE"]},
{"name":"Industrial Relations Journal","vhb_2024":"B","areas":["Org","Personal"]},
{"name":"Industrial Relations: A Journal of Economy and Society","vhb_2024":"B","areas":["Org","Personal"]},
{"name":"Industry and Innovation","vhb_2024":"B","areas":["Dienstleistung","Management","Org","TIE"]},
{"name":"INFOR: Information Systems and Operational Research","vhb_2024":"B","areas":["OR"]},
{"name":"INFORMS Journal on Optimization","vhb_2024":"B","areas":["OR","Produktion"]},
{"name":"INFORMS Transactions on Education","vhb_2024":"B","areas":["Logistik","OR","Produktion"]},
{"name":"Innovation: Organization &amp; Management","vhb_2024":"B","areas":["Org"]},
{"name":"Insurance: Mathematics &amp; Economics","vhb_2024":"B","areas":["Finance"]},
{"name":"International Business Review","vhb_2024":"B","areas":["Int. Management","Management","Marketing","Org","Personal"]},
{"name":"International Economic Review","vhb_2024":"A","areas":["Finance"]},
{"name":"International Journal of Auditing","vhb_2024":"B","areas":["Accounting"]},
{"name":"International Journal of Entrepreneurial Behaviour and Research","vhb_2024":"B","areas":["Management","TIE"]},
{"name":"International Journal of Forecasting","vhb_2024":"B","areas":["OR"]},
{"name":"International Journal of Health Economics and Management","vhb_2024":"B","areas":["Öffentliche BWL"]},
{"name":"International Journal of Human Resource Management","vhb_2024":"A","areas":["Int. Management","Management","Org","Personal"]},
{"name":"International Journal of Humanitarian Logistics and Supply Chain Management","vhb_2024":"B","areas":["Logistik"]},
{"name":"International Journal of Industrial Organization","vhb_2024":"B","areas":["Dienstleistung"]},
{"name":"International Journal of Life Cycle Assessment","vhb_2024":"B","areas":["Nachhaltigkeit"]},
{"name":"International Journal of Logistics Management","vhb_2024":"B","areas":["Dienstleistung","Logistik","Produktion"]},
{"name":"International Journal of Management Reviews","vhb_2024":"B","areas":["Dienstleistung","Int. Management","Management","Nachhaltigkeit","Org","Personal","TIE","WI"]},
{"name":"International Journal of Operations &amp; Production Management","vhb_2024":"B","areas":["Dienstleistung","Logistik","OR","Produktion","TIE"]},
{"name":"International Journal of Physical Distribution &amp; Logistics Management","vhb_2024":"B","areas":["Dienstleistung","Logistik","Produktion"]},
{"name":"International Journal of Production Economics","vhb_2024":"B","areas":["Dienstleistung","Logistik","OR","Produktion"]},
{"name":"International Journal of Production Research","vhb_2024":"B","areas":["Logistik","OR","Produktion"]},
{"name":"International Journal of Project Management","vhb_2024":"B","areas":["Org","Personal"]},
{"name":"International Journal of Public Administration","vhb_2024":"B","areas":["Öffentliche BWL"]},
{"name":"International Journal of Public Sector Management","vhb_2024":"B","areas":["Öffentliche BWL"]},
{"name":"International Journal of Research in Marketing","vhb_2024":"A","areas":["Dienstleistung","Marketing","TIE"]},
{"name":"International Journal of Selection and Assessment","vhb_2024":"B","areas":["Personal"]},
{"name":"International Journal of Technology Assessment in Health Care","vhb_2024":"B","areas":["Öffentliche BWL"]},
{"name":"International Labour Review","vhb_2024":"B","areas":["Personal"]},
{"name":"International Marketing Review","vhb_2024":"B","areas":["Dienstleistung","Int. Management","Marketing"]},
{"name":"International Public Management Journal","vhb_2024":"B","areas":["Öffentliche BWL"]},
{"name":"International Review of Administrative Sciences","vhb_2024":"B","areas":["Öffentliche BWL"]},
{"name":"International Review of Financial Analysis","vhb_2024":"B","areas":["Finance"]},
{"name":"International Review of Law and Economics","vhb_2024":"B","areas":["Accounting","Finance"]},
{"name":"International Small Business Journal","vhb_2024":"B","areas":["Dienstleistung","Management","Org","TIE"]},
{"name":"International Tax and Public Finance","vhb_2024":"B","areas":["Steuern","Öffentliche BWL"]},
{"name":"International Transactions in Operational Research","vhb_2024":"B","areas":["Logistik","OR","Produktion"]},
{"name":"Internationale Steuer-Rundschau (ISR)","vhb_2024":"B","areas":["Steuern"]},
{"name":"Internationales Steuerrecht (iStR)","vhb_2024":"B","areas":["Steuern"]},
{"name":"Intertax","vhb_2024":"B","areas":["Steuern"]},
{"name":"Issues in Accounting Education","vhb_2024":"B","areas":["Accounting"]},
{"name":"Jahrbücher für Nationalökonomie und Statistik","vhb_2024":"B","areas":["Steuern"]},
{"name":"Journal of Accounting &amp; Organizational Change","vhb_2024":"B","areas":["Accounting"]},
{"name":"Journal of Accounting and Economics","vhb_2024":"A+","areas":["Accounting","Finance","Steuern"]},
{"name":"Journal of Accounting and Public Policy","vhb_2024":"B","areas":["Accounting","Steuern","Öffentliche BWL"]},
{"name":"Journal of Accounting Literature","vhb_2024":"B","areas":["Accounting"]},
{"name":"Journal of Accounting Research","vhb_2024":"A+","areas":["Accounting","Finance","Steuern"]},
{"name":"Journal of Accounting, Auditing &amp; Finance","vhb_2024":"B","areas":["Accounting","Finance","Steuern"]},
{"name":"Journal of Advertising","vhb_2024":"B","areas":["Marketing"]},
{"name":"Journal of Advertising Research","vhb_2024":"B","areas":["Marketing"]},
{"name":"Journal of Air Transport Management","vhb_2024":"B","areas":["Logistik"]},
{"name":"Journal of Alternative Investments","vhb_2024":"B","areas":["Finance"]},
{"name":"Journal of Applied Corporate Finance","vhb_2024":"B","areas":["Finance"]},
{"name":"Journal of Applied Psychology","vhb_2024":"A+","areas":["Int. Management","Marketing","Personal"]},
{"name":"Journal of Applied Social Psychology","vhb_2024":"B","areas":["Personal"]},
{"name":"Journal of Asset Management","vhb_2024":"B","areas":["Finance"]},
{"name":"Journal of Banking &amp; Finance","vhb_2024":"A","areas":["Finance","Steuern"]},
{"name":"Journal of Behavioral and Experimental Economics","vhb_2024":"B","areas":["Finance","Personal"]},
{"name":"Journal of Behavioral Decision Making","vhb_2024":"B","areas":["Marketing"]},
{"name":"Journal of Behavioral Finance","vhb_2024":"B","areas":["Finance","Steuern"]},
{"name":"Journal of Behavioral Public Administration","vhb_2024":"B","areas":["Öffentliche BWL"]},
{"name":"Journal of Business and Psychology","vhb_2024":"B","areas":["Org","Personal"]},
{"name":"Journal of Business Economics","vhb_2024":"B","areas":["Accounting","Finance","Int. Management","Logistik","Marketing","Nachhaltigkeit","OR","Org","Personal","Produktion","Steuern","TIE","WI","Wissenschaftstheorie"]},
{"name":"Journal of Business Ethics","vhb_2024":"A","areas":["Accounting","Dienstleistung","Finance","Int. Management","Management","Marketing","Nachhaltigkeit","Org","Personal","Steuern","TIE","WI","Wissenschaftstheorie"]},
{"name":"Journal of Business Finance &amp; Accounting","vhb_2024":"B","areas":["Accounting","Finance","Steuern"]},
{"name":"Journal of Business Logistics","vhb_2024":"A","areas":["Dienstleistung","Logistik"]},
{"name":"Journal of Business Research","vhb_2024":"A","areas":["Accounting","Dienstleistung","Finance","Int. Management","Management","Marketing","Nachhaltigkeit","OR","Org","Personal","Steuern","TIE","WI","Wissenschaftstheorie"]},
{"name":"Journal of Business Venturing","vhb_2024":"A","areas":["Management","Org","TIE"]},
{"name":"Journal of Business Venturing Design","vhb_2024":"B","areas":["Management","Org","TIE"]},
{"name":"Journal of Business Venturing Insights","vhb_2024":"B","areas":["Management","Org","TIE"]},
{"name":"Journal of Commodity Markets","vhb_2024":"B","areas":["Finance"]},
{"name":"Journal of Computational Finance","vhb_2024":"B","areas":["Finance"]},
{"name":"Journal of Consumer Behaviour","vhb_2024":"B","areas":["Dienstleistung","Marketing"]},
{"name":"Journal of Consumer Psychology","vhb_2024":"A","areas":["Dienstleistung","Marketing"]},
{"name":"Journal of Consumer Research","vhb_2024":"A+","areas":["Dienstleistung","Marketing"]},
{"name":"Journal of Corporate Finance","vhb_2024":"A","areas":["Finance","Steuern","TIE"]},
{"name":"Journal of Credit Risk","vhb_2024":"B","areas":["Finance"]},
{"name":"Journal of Cross-Cultural Psychology","vhb_2024":"B","areas":["Int. Management","Personal"]},
{"name":"Journal of Cultural Economics","vhb_2024":"B","areas":["Dienstleistung"]},
{"name":"Journal of Derivatives","vhb_2024":"B","areas":["Finance"]},
{"name":"Journal of Econometrics","vhb_2024":"A","areas":["Finance"]},
{"name":"Journal of Economic Behavior &amp; Organization","vhb_2024":"A","areas":["Accounting","Finance","Marketing","Org","Personal","Steuern","TIE"]},
{"name":"Journal of Economic Dynamics &amp; Control","vhb_2024":"A","areas":["Finance"]},
{"name":"Journal of Economic Literature","vhb_2024":"A","areas":["Finance"]},
{"name":"Journal of Economic Perspectives","vhb_2024":"A","areas":["Finance"]},
{"name":"Journal of Economic Psychology","vhb_2024":"B","areas":["Finance","Management","Marketing","Org","Personal"]},
{"name":"Journal of Economic Theory","vhb_2024":"A","areas":["Finance"]},
{"name":"Journal of Economics and Management Strategy","vhb_2024":"B","areas":["Int. Management","Management","TIE"]},
{"name":"Journal of Emerging Technologies in Accounting","vhb_2024":"B","areas":["Accounting"]},
{"name":"Journal of Empirical Finance","vhb_2024":"B","areas":["Finance"]},
{"name":"Journal of Entrepreneurship","vhb_2024":"B","areas":["Org"]},
{"name":"Journal of Environmental Economics and Management","vhb_2024":"B","areas":["Nachhaltigkeit"]},
{"name":"Journal of Environmental Management","vhb_2024":"B","areas":["Logistik","Nachhaltigkeit"]},
{"name":"Journal of Environmental Planning and Management","vhb_2024":"B","areas":["Nachhaltigkeit"]},
{"name":"Journal of European Public Policy","vhb_2024":"A","areas":["Öffentliche BWL"]},
{"name":"Journal of European Social Policy","vhb_2024":"B","areas":["Öffentliche BWL"]},
{"name":"Journal of Experimental Social Psychology","vhb_2024":"A","areas":["Management","Marketing"]},
{"name":"Journal of Family Business Strategy","vhb_2024":"B","areas":["Management","Org","TIE"]},
{"name":"Journal of Financial and Quantitative Analysis","vhb_2024":"A","areas":["Accounting","Finance","Steuern"]},
{"name":"Journal of Financial Econometrics","vhb_2024":"B","areas":["Finance"]},
{"name":"Journal of Financial Economics","vhb_2024":"A+","areas":["Accounting","Finance","Steuern"]},
{"name":"Journal of Financial Intermediation","vhb_2024":"A","areas":["Finance"]},
{"name":"Journal of Financial Markets","vhb_2024":"B","areas":["Finance"]},
{"name":"Journal of Financial Reporting","vhb_2024":"B","areas":["Accounting"]},
{"name":"Journal of Financial Research","vhb_2024":"B","areas":["Finance"]},
{"name":"Journal of Financial Services Research","vhb_2024":"B","areas":["Finance"]},
{"name":"Journal of Financial Stability","vhb_2024":"A","areas":["Finance"]},
{"name":"Journal of Fixed Income","vhb_2024":"B","areas":["Finance"]},
{"name":"Journal of Forecasting","vhb_2024":"B","areas":["Marketing","OR"]},
{"name":"Journal of Futures Markets","vhb_2024":"B","areas":["Finance"]},
{"name":"Journal of Governmental &amp; Nonprofit Accounting","vhb_2024":"B","areas":["Accounting"]},
{"name":"Journal of Health Economics","vhb_2024":"A+","areas":["Öffentliche BWL"]},
{"name":"Journal of Health Services Research &amp; Policy","vhb_2024":"B","areas":["Öffentliche BWL"]},
{"name":"Journal of Heuristics","vhb_2024":"B","areas":["OR"]},
{"name":"Journal of Human Resources","vhb_2024":"B","areas":["Personal"]},
{"name":"Journal of Industrial Ecology","vhb_2024":"A","areas":["Logistik","Nachhaltigkeit","OR"]},
{"name":"Journal of Industrial Economics","vhb_2024":"B","areas":["Dienstleistung"]},
{"name":"Journal of Industrial Relations","vhb_2024":"B","areas":["Personal"]},
{"name":"Journal of Information Systems","vhb_2024":"B","areas":["Accounting"]},
{"name":"Journal of Institutional and Theoretical Economics","vhb_2024":"B","areas":["Steuern","Wissenschaftstheorie"]},
{"name":"Journal of International Accounting Auditing and Taxation","vhb_2024":"B","areas":["Accounting","Steuern"]},
{"name":"Journal of International Accounting Research","vhb_2024":"B","areas":["Accounting"]},
{"name":"Journal of International Business Policy","vhb_2024":"B","areas":["Int. Management"]},
{"name":"Journal of International Business Studies","vhb_2024":"A","areas":["Int. Management","Management","Marketing","Org","Personal","TIE"]},
{"name":"Journal of International Economics","vhb_2024":"A","areas":["Finance"]},
{"name":"Journal of International Financial Management and Accounting","vhb_2024":"B","areas":["Accounting"]},
{"name":"Journal of International Financial Markets, Institutions and Money","vhb_2024":"B","areas":["Finance"]},
{"name":"Journal of International Management","vhb_2024":"B","areas":["Int. Management","Management","Org"]},
{"name":"Journal of International Marketing","vhb_2024":"B","areas":["Int. Management","Marketing"]},
{"name":"Journal of International Money and Finance","vhb_2024":"B","areas":["Finance"]},
{"name":"Journal of Labor Economics","vhb_2024":"A","areas":["Finance","Personal"]},
{"name":"Journal of Law &amp; Economics","vhb_2024":"A","areas":["Finance","Steuern"]},
{"name":"Journal of Law, Economics and Organization","vhb_2024":"B","areas":["Finance"]},
{"name":"Journal of Leadership &amp; Organizational Studies","vhb_2024":"B","areas":["Org","Personal"]},
{"name":"Journal of Management","vhb_2024":"A","areas":["Accounting","Dienstleistung","Int. Management","Logistik","Management","Marketing","Nachhaltigkeit","OR","Org","Personal","TIE","WI","Wissenschaftstheorie"]},
{"name":"Journal of Management &amp; Organization","vhb_2024":"B","areas":["Management","Org","Personal"]},
{"name":"Journal of Management Accounting Research","vhb_2024":"A","areas":["Accounting","Steuern"]},
{"name":"Journal of Management Control","vhb_2024":"B","areas":["Accounting"]},
{"name":"Journal of Management Inquiry","vhb_2024":"B","areas":["Int. Management","Management","Nachhaltigkeit","Org","Personal","Wissenschaftstheorie"]},
{"name":"Journal of Management Studies","vhb_2024":"A","areas":["Accounting","Dienstleistung","Int. Management","Logistik","Management","Marketing","Nachhaltigkeit","Org","Personal","TIE","WI","Wissenschaftstheorie"]},
{"name":"Journal of Managerial Psychology","vhb_2024":"B","areas":["Org","Personal"]},
{"name":"Journal of Marketing","vhb_2024":"A+","areas":["Dienstleistung","Marketing","TIE"]},
{"name":"Journal of Marketing Research","vhb_2024":"A+","areas":["Dienstleistung","Marketing","TIE"]},
{"name":"Journal of Marketing Theory and Practice","vhb_2024":"B","areas":["Dienstleistung","Marketing"]},
{"name":"Journal of Media Economics","vhb_2024":"B","areas":["Marketing"]},
{"name":"Journal of Monetary Economics","vhb_2024":"A","areas":["Finance"]},
{"name":"Journal of Money, Credit and Banking","vhb_2024":"A","areas":["Finance"]},
{"name":"Journal of Multi-Criteria Decision Analysis","vhb_2024":"B","areas":["OR"]},
{"name":"Journal of Occupational and Organizational Psychology","vhb_2024":"B","areas":["Org","Personal"]},
{"name":"Journal of Occupational Health Psychology","vhb_2024":"B","areas":["Org","Personal"]},
{"name":"Journal of Organization Design","vhb_2024":"B","areas":["Management"]},
{"name":"Journal of Organizational Behavior","vhb_2024":"A","areas":["Org","Personal","TIE"]},
{"name":"Journal of Organizational Behavior Management","vhb_2024":"B","areas":["Personal"]},
{"name":"Journal of Organizational Change Management","vhb_2024":"B","areas":["Management","Personal"]},
{"name":"Journal of Organizational Sociology","vhb_2024":"B","areas":["Org","Personal"]},
{"name":"Journal of Personal Selling &amp; Sales Management","vhb_2024":"B","areas":["Dienstleistung","Marketing"]},
{"name":"Journal of Personality and Social Psychology","vhb_2024":"A+","areas":["Marketing","Personal"]},
{"name":"Journal of Personnel Psychology","vhb_2024":"B","areas":["Personal"]},
{"name":"Journal of Policy Analysis and Management","vhb_2024":"B","areas":["Öffentliche BWL"]},
{"name":"Journal of Political Economy","vhb_2024":"A+","areas":["Finance","Int. Management","Marketing","Wissenschaftstheorie"]},
{"name":"Journal of Product Innovation Management","vhb_2024":"A","areas":["Dienstleistung","Management","Marketing","Org","TIE","WI"]},
{"name":"Journal of Professions and Organization","vhb_2024":"B","areas":["Org"]},
{"name":"Journal of Public Administration Research and Theory","vhb_2024":"A","areas":["TIE","Öffentliche BWL"]},
{"name":"Journal of Public Economic Theory","vhb_2024":"B","areas":["Steuern"]},
{"name":"Journal of Public Economics","vhb_2024":"A","areas":["Finance","Steuern","Öffentliche BWL"]},
{"name":"Journal of Public Policy &amp; Marketing","vhb_2024":"B","areas":["Dienstleistung","Marketing","Öffentliche BWL"]},
{"name":"Journal of Purchasing &amp; Supply Management","vhb_2024":"B","areas":["Dienstleistung","Logistik","Produktion"]},
{"name":"Journal of Retailing","vhb_2024":"A","areas":["Dienstleistung","Logistik","Marketing","OR"]},
{"name":"Journal of Retailing and Consumer Services","vhb_2024":"B","areas":["Dienstleistung","Logistik","Marketing"]},
{"name":"Journal of Risk","vhb_2024":"B","areas":["Accounting","Finance"]},
{"name":"Journal of Risk and Insurance","vhb_2024":"A","areas":["Accounting","Finance"]},
{"name":"Journal of Risk and Uncertainty","vhb_2024":"B","areas":["Accounting","Finance","OR"]},
{"name":"Journal of Risk Finance","vhb_2024":"B","areas":["Accounting","Finance"]},
{"name":"Journal of Scheduling","vhb_2024":"A","areas":["Logistik","OR"]},
{"name":"Journal of Small Business Management","vhb_2024":"B","areas":["Dienstleistung","Management","Org","TIE"]},
{"name":"Journal of Supply Chain Management","vhb_2024":"B","areas":["Dienstleistung","Logistik","Produktion","TIE"]},
{"name":"Journal of Sustainable Finance &amp; Investment","vhb_2024":"B","areas":["Finance"]},
{"name":"Journal of the Academy of Marketing Science","vhb_2024":"A","areas":["Dienstleistung","Marketing","TIE"]},
{"name":"Journal of the Association for Consumer Research","vhb_2024":"B","areas":["Marketing"]},
{"name":"Journal of the European Economic Association","vhb_2024":"A","areas":["Finance","Steuern"]},
{"name":"Journal of the Operational Research Society","vhb_2024":"B","areas":["Logistik","OR","Produktion"]},
{"name":"Journal of Transport Geography","vhb_2024":"B","areas":["Logistik"]},
{"name":"Journal of Travel Research","vhb_2024":"B","areas":["Dienstleistung","Management","Marketing"]},
{"name":"Journal of Vocational Behavior","vhb_2024":"A","areas":["Org","Personal"]},
{"name":"Journal of World Business","vhb_2024":"A","areas":["Int. Management","Management","Org","Personal","TIE"]},
{"name":"Kyklos","vhb_2024":"B","areas":["Int. Management","Org","Personal","Wissenschaftstheorie"]},
{"name":"Kölner Zeitschrift für Soziologie und Sozialpsychologie","vhb_2024":"B","areas":["Org"]},
{"name":"Labour Economics","vhb_2024":"B","areas":["Personal"]},
{"name":"Labour: Review of Labour Economics and Industrial Relations","vhb_2024":"B","areas":["Personal"]},
{"name":"Leadership","vhb_2024":"B","areas":["Org","Personal"]},
{"name":"Leviathan: Berliner Zeitschrift für Sozialwissenschaft","vhb_2024":"B","areas":["Org"]},
{"name":"Local Government Studies","vhb_2024":"B","areas":["Öffentliche BWL"]},
{"name":"Long Range Planning","vhb_2024":"B","areas":["Accounting","Dienstleistung","Int. Management","Logistik","Management","Marketing","OR","Org","Personal","TIE","WI","Wissenschaftstheorie"]},
{"name":"M@n@gement","vhb_2024":"B","areas":["Org","Personal"]},
{"name":"Management Accounting Research","vhb_2024":"A","areas":["Accounting","Steuern","TIE"]},
{"name":"Management and Organization Review","vhb_2024":"B","areas":["Org","Personal"]},
{"name":"Management Decision","vhb_2024":"B","areas":["Dienstleistung","Int. Management","Logistik","Management","Marketing","OR","Org","Personal","TIE"]},
{"name":"Management International Review","vhb_2024":"B","areas":["Int. Management","Management","Org","Personal"]},
{"name":"Management Learning","vhb_2024":"B","areas":["Management","Org","Personal"]},
{"name":"Management Review Quarterly","vhb_2024":"B","areas":["Dienstleistung","Int. Management","Management","Marketing","Nachhaltigkeit","OR","TIE","WI","Wissenschaftstheorie"]},
{"name":"Management Revue - Socio-Economic Studies","vhb_2024":"B","areas":["Personal","Wissenschaftstheorie"]},
{"name":"Managementforschung","vhb_2024":"B","areas":["Org","Personal"]},
{"name":"Managerial and Decision Economics","vhb_2024":"B","areas":["Accounting","Steuern"]},
{"name":"Managerial Auditing Journal","vhb_2024":"B","areas":["Accounting"]},
{"name":"Maritime Transport Research","vhb_2024":"B","areas":["Logistik"]},
{"name":"Marketing Letters","vhb_2024":"B","areas":["Dienstleistung","Marketing"]},
{"name":"Marketing Science","vhb_2024":"A+","areas":["Marketing","TIE"]},
{"name":"Marketing Theory","vhb_2024":"B","areas":["Dienstleistung","Marketing"]},
{"name":"Mathematical Finance","vhb_2024":"B","areas":["Finance"]},
{"name":"Mathematical Methods of Operations Research","vhb_2024":"B","areas":["OR"]},
{"name":"Mathematical Programming","vhb_2024":"A","areas":["OR"]},
{"name":"Mathematics of Operations Research","vhb_2024":"A","areas":["OR"]},
{"name":"Medical Care","vhb_2024":"B","areas":["Öffentliche BWL"]},
{"name":"Medical Decision Making","vhb_2024":"A","areas":["Öffentliche BWL"]},
{"name":"Multivariate Behavioral Research","vhb_2024":"B","areas":["Marketing"]},
{"name":"National Tax Journal","vhb_2024":"A","areas":["Steuern"]},
{"name":"Nature","vhb_2024":"A+","areas":["Marketing","Nachhaltigkeit","WI"]},
{"name":"Nature Climate Change","vhb_2024":"A","areas":["Nachhaltigkeit"]},
{"name":"Nature Communications","vhb_2024":"A","areas":["Marketing","WI"]},
{"name":"Nature Energy","vhb_2024":"A","areas":["Nachhaltigkeit","WI"]},
{"name":"Nature Sustainability","vhb_2024":"A","areas":["Nachhaltigkeit","WI"]},
{"name":"Naval Research Logistics","vhb_2024":"B","areas":["Logistik","OR"]},
{"name":"Networks","vhb_2024":"A","areas":["Logistik","OR"]},
{"name":"Networks and Spatial Economics","vhb_2024":"B","areas":["Logistik"]},
{"name":"New Technology, Work and Employment","vhb_2024":"B","areas":["Personal"]},
{"name":"Nonprofit and Voluntary Sector Quarterly","vhb_2024":"A","areas":["Dienstleistung","Öffentliche BWL"]},
{"name":"Nonprofit Management &amp; Leadership","vhb_2024":"B","areas":["Personal","Öffentliche BWL"]},
{"name":"Nonprofit Policy Forum","vhb_2024":"B","areas":["Öffentliche BWL"]},
{"name":"Nordic Tax Journal","vhb_2024":"B","areas":["Steuern"]},
{"name":"North American Actuarial Journal","vhb_2024":"B","areas":["Finance"]},
{"name":"Operations Research Forum","vhb_2024":"B","areas":["OR"]},
{"name":"Optimization Letters","vhb_2024":"B","areas":["OR"]},
{"name":"Organization","vhb_2024":"B","areas":["Management","Org","Personal","WI"]},
{"name":"Organization &amp; Environment","vhb_2024":"B","areas":["Management","Nachhaltigkeit","Personal"]},
{"name":"Organization Studies","vhb_2024":"A","areas":["Accounting","Dienstleistung","Int. Management","Logistik","Management","Marketing","Org","Personal","TIE","WI","Wissenschaftstheorie"]},
{"name":"Organization Theory","vhb_2024":"A","areas":["Management","Org","Personal"]},
{"name":"Organizational Behavior and Human Decision Processes","vhb_2024":"A","areas":["Org","Personal"]},
{"name":"Organizational Dynamics","vhb_2024":"B","areas":["Management","Org","Personal"]},
{"name":"Organizational Psychology Review","vhb_2024":"B","areas":["Org","Personal"]},
{"name":"Organizational Research Methods","vhb_2024":"A","areas":["Management","Marketing","Org","Personal","TIE"]},
{"name":"Personality and Individual Differences","vhb_2024":"B","areas":["Personal"]},
{"name":"Personality and Social Psychology Bulletin","vhb_2024":"A","areas":["Personal"]},
{"name":"Personnel Psychology","vhb_2024":"A","areas":["Org","Personal"]},
{"name":"Personnel Review","vhb_2024":"B","areas":["Org","Personal"]},
{"name":"Perspectives on Public Management and Governance","vhb_2024":"B","areas":["Öffentliche BWL"]},
{"name":"PharmacoEconomics","vhb_2024":"A","areas":["Öffentliche BWL"]},
{"name":"PLOS One","vhb_2024":"B","areas":["Int. Management","Management","Marketing","Nachhaltigkeit","OR","Org","WI","Öffentliche BWL"]},
{"name":"Proceedings of the National Academy of Sciences","vhb_2024":"A","areas":["Marketing"]},
{"name":"Production Planning &amp; Control","vhb_2024":"B","areas":["Dienstleistung","Produktion"]},
{"name":"Project Management Journal","vhb_2024":"B","areas":["Org","Personal"]},
{"name":"Psychological Methods","vhb_2024":"A","areas":["Marketing"]},
{"name":"Psychological Science","vhb_2024":"A+","areas":["Marketing"]},
{"name":"Psychology &amp; Marketing","vhb_2024":"B","areas":["Dienstleistung","Marketing"]},
{"name":"Psychometrika","vhb_2024":"A","areas":["Marketing"]},
{"name":"Public Administration","vhb_2024":"A","areas":["Accounting","Öffentliche BWL"]},
{"name":"Public Administration Review","vhb_2024":"A","areas":["Öffentliche BWL"]},
{"name":"Public Finance Review","vhb_2024":"B","areas":["Steuern","Öffentliche BWL"]},
{"name":"Public Management Review","vhb_2024":"A","areas":["Accounting","Öffentliche BWL"]},
{"name":"Public Money &amp; Management","vhb_2024":"B","areas":["Öffentliche BWL"]},
{"name":"Public Performance &amp; Management Review","vhb_2024":"B","areas":["Öffentliche BWL"]},
{"name":"Public Policy and Administration","vhb_2024":"B","areas":["Öffentliche BWL"]},
{"name":"Qualitative Research in Accounting &amp; Management","vhb_2024":"B","areas":["Accounting","Dienstleistung"]},
{"name":"Quantitative Finance","vhb_2024":"B","areas":["Finance"]},
{"name":"Quantitative Marketing and Economics","vhb_2024":"A","areas":["Marketing"]},
{"name":"Quarterly Journal of Economics","vhb_2024":"A+","areas":["Finance"]},
{"name":"R&amp;D Management","vhb_2024":"B","areas":["Dienstleistung","Management","Marketing","Org","TIE"]},
{"name":"Real Estate Economics","vhb_2024":"B","areas":["Finance"]},
{"name":"Regional Studies","vhb_2024":"B","areas":["Org"]},
{"name":"Relations Industrielles / Industrial Relations","vhb_2024":"B","areas":["Personal"]},
{"name":"Renewable and Sustainable Energy Reviews","vhb_2024":"B","areas":["Nachhaltigkeit"]},
{"name":"Research in Higher Education","vhb_2024":"B","areas":["Hochschulmanagement"]},
{"name":"Research in Organizational Behavior","vhb_2024":"B","areas":["Management","Org","Personal"]},
{"name":"Research in the Sociology of Organizations","vhb_2024":"B","areas":["Management","Org","Personal"]},
{"name":"Research Policy","vhb_2024":"A","areas":["Management","Marketing","Nachhaltigkeit","Org","Personal","TIE","WI"]},
{"name":"Resource and Energy Economics","vhb_2024":"B","areas":["Nachhaltigkeit"]},
{"name":"Resources, Conservation and Recycling","vhb_2024":"B","areas":["Nachhaltigkeit"]},
{"name":"Review of Accounting and Finance","vhb_2024":"B","areas":["Accounting"]},
{"name":"Review of Accounting Studies","vhb_2024":"A","areas":["Accounting","Finance","Steuern"]},
{"name":"Review of Derivatives Research","vhb_2024":"A","areas":["Finance"]},
{"name":"Review of Economic Studies","vhb_2024":"A+","areas":["Finance"]},
{"name":"Review of Finance","vhb_2024":"A","areas":["Finance","Steuern"]},
{"name":"Review of Financial Economics","vhb_2024":"B","areas":["Finance"]},
{"name":"Review of Managerial Science","vhb_2024":"B","areas":["Accounting","Dienstleistung","Finance","Int. Management","Logistik","Management","Marketing","Nachhaltigkeit","OR","Org","Personal","Produktion","Steuern","TIE","WI"]},
{"name":"Review of Public Personnel Administration","vhb_2024":"B","areas":["Öffentliche BWL"]},
{"name":"Review of Quantitative Finance and Accounting","vhb_2024":"B","areas":["Accounting","Finance","Steuern"]},
{"name":"Scandinavian Journal of Management","vhb_2024":"B","areas":["Accounting","Dienstleistung","Int. Management","Management","Marketing","Nachhaltigkeit","Org","Personal","TIE","WI","Wissenschaftstheorie"]},
{"name":"Schmalenbach Business Review","vhb_2024":"B","areas":["Finance","Org","Personal"]},
{"name":"Schmalenbach Journal of Business Research","vhb_2024":"B","areas":["Accounting","Dienstleistung","Finance","Int. Management","Logistik","Management","Marketing","Nachhaltigkeit","OR","Org","Personal","Produktion","Steuern","TIE","WI","Wissenschaftstheorie"]},
{"name":"Science","vhb_2024":"A+","areas":["Finance","Int. Management","Logistik","Marketing","Nachhaltigkeit","OR","WI","Wissenschaftstheorie"]},
{"name":"Scientometrics","vhb_2024":"B","areas":["TIE"]},
{"name":"Small Business Economics","vhb_2024":"B","areas":["Accounting","Dienstleistung","Management","Org","TIE"]},
{"name":"Social and Environmental Accountability Journal","vhb_2024":"B","areas":["Nachhaltigkeit"]},
{"name":"Social Forces","vhb_2024":"B","areas":["Org"]},
{"name":"Social Science &amp; Medicine","vhb_2024":"A","areas":["Öffentliche BWL"]},
{"name":"Society and Business Review","vhb_2024":"B","areas":["Wissenschaftstheorie"]},
{"name":"Socio-Economic Review","vhb_2024":"B","areas":["Org","Personal"]},
{"name":"Soziale Systeme: Zeitschrift für soziologische Theorie","vhb_2024":"B","areas":["Org"]},
{"name":"Steuer und Wirtschaft","vhb_2024":"A","areas":["Steuern"]},
{"name":"Strategic Change","vhb_2024":"B","areas":["Management"]},
{"name":"Strategic Entrepreneurship Journal","vhb_2024":"A","areas":["Dienstleistung","Management","Org","TIE"]},
{"name":"Strategic Management Journal","vhb_2024":"A+","areas":["Accounting","Dienstleistung","Finance","Int. Management","Logistik","Management","Marketing","OR","Org","Personal","TIE","WI","Wissenschaftstheorie"]},
{"name":"Strategic Management Review","vhb_2024":"B","areas":["Int. Management","Management","Org"]},
{"name":"Strategic Organization","vhb_2024":"B","areas":["Management","Org","Personal"]},
{"name":"Strategy Science","vhb_2024":"A","areas":["Int. Management","Management","Org"]},
{"name":"Structural Equation Modeling: A Multidisciplinary Journal","vhb_2024":"B","areas":["Marketing"]},
{"name":"Studies in Higher Education","vhb_2024":"A","areas":["Hochschulmanagement","Org"]},
{"name":"Supply Chain Management: An International Journal","vhb_2024":"B","areas":["Dienstleistung","Logistik","Produktion"]},
{"name":"Sustainability Accounting, Management and Policy Journal","vhb_2024":"B","areas":["Nachhaltigkeit"]},
{"name":"Sustainability Analytics and Modeling","vhb_2024":"B","areas":["Dienstleistung","Logistik","Nachhaltigkeit","OR","Produktion"]},
{"name":"Sustainability Science","vhb_2024":"B","areas":["Nachhaltigkeit"]},
{"name":"Sustainable Development","vhb_2024":"B","areas":["Nachhaltigkeit"]},
{"name":"Sustainable Production and Consumption","vhb_2024":"B","areas":["Nachhaltigkeit"]},
{"name":"SWI - Steuer und Wirtschaft International","vhb_2024":"B","areas":["Steuern"]},
{"name":"System Dynamics Review","vhb_2024":"B","areas":["Logistik","OR","Produktion","Öffentliche BWL"]},
{"name":"The American Review of Public Administration","vhb_2024":"B","areas":["Öffentliche BWL"]},
{"name":"The British Accounting Review","vhb_2024":"B","areas":["Accounting"]},
{"name":"The Economic Journal","vhb_2024":"A","areas":["Finance","Steuern"]},
{"name":"The Energy Journal","vhb_2024":"B","areas":["Nachhaltigkeit"]},
{"name":"The European Journal of Health Economics","vhb_2024":"A","areas":["Öffentliche BWL"]},
{"name":"The International Journal of Accounting","vhb_2024":"B","areas":["Accounting"]},
{"name":"The International Journal of Advanced Manufacturing Technology","vhb_2024":"B","areas":["Logistik","Produktion"]},
{"name":"The Journal of Applied Behavioral Science","vhb_2024":"B","areas":["Personal"]},
{"name":"The Journal of Finance","vhb_2024":"A+","areas":["Finance","Steuern"]},
{"name":"The Journal of Portfolio Management","vhb_2024":"B","areas":["Accounting","Finance"]},
{"name":"The Journal of Technology Transfer","vhb_2024":"B","areas":["Dienstleistung","Management","TIE"]},
{"name":"The Journal of the American Taxation Association","vhb_2024":"B","areas":["Steuern"]},
{"name":"The Leadership Quarterly","vhb_2024":"A","areas":["Int. Management","Management","Org","Personal","TIE"]},
{"name":"The Quarterly Review of Economics and Finance","vhb_2024":"B","areas":["Finance"]},
{"name":"The RAND Journal of Economics","vhb_2024":"A","areas":["Finance","Int. Management","Marketing","OR","TIE"]},
{"name":"The Review of Asset Pricing Studies","vhb_2024":"A","areas":["Finance"]},
{"name":"The Review of Corporate Finance Studies","vhb_2024":"A","areas":["Finance"]},
{"name":"The Review of Economics and Statistics","vhb_2024":"A","areas":["Finance"]},
{"name":"The Review of Financial Studies","vhb_2024":"A+","areas":["Finance","Steuern"]},
{"name":"The Scandinavian Journal of Economics","vhb_2024":"B","areas":["Steuern"]},
{"name":"Thunderbird International Business Review","vhb_2024":"B","areas":["Personal"]},
{"name":"Tourism Management","vhb_2024":"B","areas":["Dienstleistung","Management","Marketing"]},
{"name":"Transport Policy","vhb_2024":"B","areas":["Logistik"]},
{"name":"Transportation","vhb_2024":"B","areas":["Logistik"]},
{"name":"Transportation Research Part A: Policy and Practice","vhb_2024":"B","areas":["Dienstleistung","Logistik","Marketing"]},
{"name":"Transportation Research Part B: Methodological","vhb_2024":"A","areas":["Logistik","OR"]},
{"name":"Transportation Research Part C: Emerging Technologies","vhb_2024":"B","areas":["Logistik","OR"]},
{"name":"Transportation Research Part D: Transport and Environment","vhb_2024":"B","areas":["Logistik","Nachhaltigkeit","OR"]},
{"name":"Transportation Research Part E: Logistics and Transportation Review","vhb_2024":"B","areas":["Logistik","OR"]},
{"name":"Transportation Research Part F: Traffic Psychology and Behaviour","vhb_2024":"B","areas":["Logistik"]},
{"name":"Umsatzsteuer Rundschau","vhb_2024":"B","areas":["Steuern"]},
{"name":"Urban Studies","vhb_2024":"B","areas":["Öffentliche BWL"]},
{"name":"Value in Health","vhb_2024":"A","areas":["Öffentliche BWL"]},
{"name":"Voluntary Sector Review","vhb_2024":"B","areas":["Öffentliche BWL"]},
{"name":"Voluntas: International Journal of Voluntary and Nonprofit Organizations","vhb_2024":"B","areas":["Dienstleistung","Management","Org","Öffentliche BWL"]},
{"name":"Waste Management","vhb_2024":"B","areas":["Nachhaltigkeit"]},
{"name":"Work &amp; Stress","vhb_2024":"B","areas":["Org","Personal"]},
{"name":"Work and Occupations","vhb_2024":"B","areas":["Org","Personal"]},
{"name":"Work, Aging and Retirement","vhb_2024":"B","areas":["Personal"]},
{"name":"Work, Employment and Society","vhb_2024":"B","areas":["Org","Personal"]},
{"name":"World Tax Journal","vhb_2024":"B","areas":["Steuern"]},
{"name":"Zeitschrift für Umweltpolitik &amp; Umweltrecht","vhb_2024":"B","areas":["Nachhaltigkeit"]},
{"name":"Zeitschrift für Wirtschafts- und Unternehmensethik","vhb_2024":"B","areas":["Wissenschaftstheorie"]},
{"name":"ÖStZ - Österreichische Steuerzeitung","vhb_2024":"B","areas":["Steuern"]},
{"name":"Journal of Business","vhb_2024":"A","areas":["Finance"]},
{"name":"Journal of Cross-Cultural Management","vhb_2024":"B","areas":["Int. Management"]},
{"name":"MIS Quarterly","vhb_2024":"A+","areas":["Accounting","Dienstleistung","OR","TIE","WI"]},
{"name":"Electronic Markets","vhb_2024":"B","areas":["Dienstleistung","Logistik","Marketing","WI"]},
{"name":"Business &amp; Information Systems Engineering","vhb_2024":"B","areas":["Dienstleistung","Marketing","OR","WI"]},
{"name":"ACM SIGMIS Database: The DATA BASE for Advances in Information Systems","vhb_2024":"B","areas":["Dienstleistung","WI"]},
{"name":"ACM Transactions on Computer-Human Interaction","vhb_2024":"B","areas":["WI"]},
{"name":"ACM Transactions on Human-Robot Interaction","vhb_2024":"B","areas":["WI"]},
{"name":"ACM Transactions on Information Systems","vhb_2024":"B","areas":["WI"]},
{"name":"ACM Transactions on Interactive Intelligent Systems","vhb_2024":"B","areas":["WI"]},
{"name":"ACM Transactions on Management Information Systems","vhb_2024":"B","areas":["Dienstleistung","WI"]},
{"name":"ACM Transactions on Software Engineering and Methodology","vhb_2024":"B","areas":["WI"]},
{"name":"Administrative Science Quarterly DUP","vhb_2024":"A+","areas":["WI"]},
{"name":"AIS Transactions on Human-Computer Interaction","vhb_2024":"B","areas":["WI"]},
{"name":"Annals of Operations Research","vhb_2024":"B","areas":["Logistik","OR","Produktion","WI"]},
{"name":"Artificial Intelligence","vhb_2024":"B","areas":["WI"]},
{"name":"Behaviour &amp; Information Technology","vhb_2024":"B","areas":["WI"]},
{"name":"Communications of the ACM","vhb_2024":"B","areas":["WI"]},
{"name":"Communications of the Association for Information Systems","vhb_2024":"B","areas":["Dienstleistung","WI"]},
{"name":"Computer","vhb_2024":"B","areas":["WI"]},
{"name":"Computer Supported Cooperative Work","vhb_2024":"B","areas":["WI"]},
{"name":"Computers &amp; Education","vhb_2024":"B","areas":["WI"]},
{"name":"Computers &amp; Operations Research","vhb_2024":"B","areas":["Dienstleistung","Logistik","OR","Produktion","WI"]},
{"name":"Computers in Human Behavior","vhb_2024":"B","areas":["Dienstleistung","Marketing","Org","Personal","WI"]},
{"name":"Computers in Industry","vhb_2024":"B","areas":["Dienstleistung","Logistik","OR","Produktion","WI"]},
{"name":"Data &amp; Knowledge Engineering","vhb_2024":"B","areas":["WI"]},
{"name":"Decision Sciences","vhb_2024":"B","areas":["Logistik","OR","Produktion","TIE","WI"]},
{"name":"Decision Support Systems","vhb_2024":"B","areas":["Dienstleistung","Marketing","OR","Produktion","WI"]},
{"name":"European Journal of Information Systems","vhb_2024":"A","areas":["Dienstleistung","TIE","WI"]},
{"name":"European Journal of Operational Research","vhb_2024":"A","areas":["Dienstleistung","Logistik","OR","Produktion","WI"]},
{"name":"Expert Systems with Applications","vhb_2024":"B","areas":["OR","Produktion","WI"]},
{"name":"Government Information Quarterly","vhb_2024":"B","areas":["WI","Öffentliche BWL"]},
{"name":"Group Decision and Negotiation","vhb_2024":"B","areas":["OR","WI"]},
{"name":"Human-Computer Interaction","vhb_2024":"B","areas":["Dienstleistung","Logistik","Personal","WI"]},
{"name":"IEEE Access","vhb_2024":"B","areas":["WI"]},
{"name":"IEEE Software","vhb_2024":"B","areas":["WI"]},
{"name":"IEEE Transactions on Engineering Management","vhb_2024":"B","areas":["Dienstleistung","Org","TIE","WI"]},
{"name":"IEEE Transactions on Human-Machine Systems","vhb_2024":"B","areas":["WI"]},
{"name":"IEEE Transactions on Knowledge and Data Engineering","vhb_2024":"B","areas":["WI"]},
{"name":"IEEE Transactions on Software Engineering","vhb_2024":"B","areas":["WI"]},
{"name":"IEEE Transactions on Systems, Man, and Cybernetics: Systems","vhb_2024":"B","areas":["WI"]},
{"name":"Information &amp; Management","vhb_2024":"B","areas":["Dienstleistung","Org","TIE","WI"]},
{"name":"Information and Organization","vhb_2024":"B","areas":["Accounting","Dienstleistung","Org","TIE","WI"]},
{"name":"Information and Software Technology","vhb_2024":"B","areas":["WI"]},
{"name":"Information Systems","vhb_2024":"B","areas":["Dienstleistung","WI"]},
{"name":"Information Systems Frontiers","vhb_2024":"B","areas":["Dienstleistung","WI"]},
{"name":"Information Systems Journal","vhb_2024":"A","areas":["Dienstleistung","TIE","WI"]},
{"name":"Information Systems Management","vhb_2024":"B","areas":["Dienstleistung","WI"]},
{"name":"Information Systems Research","vhb_2024":"A+","areas":["Dienstleistung","OR","Org","TIE","WI"]},
{"name":"Information Technology &amp; People","vhb_2024":"B","areas":["WI"]},
{"name":"Information Technology and Management","vhb_2024":"B","areas":["Dienstleistung","WI"]},
{"name":"INFORMS Journal on Applied Analytics","vhb_2024":"B","areas":["Logistik","OR","Produktion","WI"]},
{"name":"INFORMS Journal on Computing","vhb_2024":"A","areas":["Logistik","OR","Produktion","WI"]},
{"name":"INFORMS Journal on Data Science","vhb_2024":"B","areas":["OR","WI"]},
{"name":"International Journal of Accounting Information Systems","vhb_2024":"B","areas":["Accounting","WI"]},
{"name":"International Journal of Electronic Commerce","vhb_2024":"B","areas":["Dienstleistung","Marketing","WI"]},
{"name":"International Journal of Human Computer Studies","vhb_2024":"B","areas":["WI"]},
{"name":"International Journal of Information Management","vhb_2024":"B","areas":["Dienstleistung","Logistik","WI"]},
{"name":"International Journal of Innovation Management","vhb_2024":"B","areas":["Dienstleistung","Management","Marketing","TIE","WI"]},
{"name":"Internet Research","vhb_2024":"B","areas":["Marketing","WI"]},
{"name":"Journal of Cleaner Production","vhb_2024":"B","areas":["Accounting","Logistik","Management","Nachhaltigkeit","OR","Org","Produktion","WI","Öffentliche BWL"]},
{"name":"Journal of Decision Systems","vhb_2024":"B","areas":["OR","WI"]},
{"name":"Journal of Information Technology","vhb_2024":"A","areas":["Dienstleistung","Org","TIE","WI"]},
{"name":"Journal of Interactive Marketing","vhb_2024":"B","areas":["Dienstleistung","Marketing","WI"]},
{"name":"Journal of Management Information Systems","vhb_2024":"A","areas":["Dienstleistung","TIE","WI"]},
{"name":"Journal of Medical Internet Research","vhb_2024":"B","areas":["Dienstleistung","WI","Öffentliche BWL"]},
{"name":"Journal of Operations Management","vhb_2024":"A","areas":["Dienstleistung","Logistik","OR","Produktion","TIE","WI"]},
{"name":"Journal of Service Management","vhb_2024":"B","areas":["Dienstleistung","Marketing","WI"]},
{"name":"Journal of Service Research","vhb_2024":"A","areas":["Dienstleistung","Marketing","TIE","WI"]},
{"name":"Journal of Strategic Information Systems","vhb_2024":"A","areas":["Dienstleistung","TIE","WI"]},
{"name":"Journal of Systems and Software","vhb_2024":"B","areas":["WI"]},
{"name":"Journal of the ACM","vhb_2024":"B","areas":["WI"]},
{"name":"Journal of the Association for Information Systems","vhb_2024":"A","areas":["Dienstleistung","TIE","WI"]},
{"name":"Management Science","vhb_2024":"A+","areas":["WI"]},
{"name":"Manufacturing &amp; Service Operations Management","vhb_2024":"A","areas":["Dienstleistung","Logistik","OR","Produktion","TIE","WI"]},
{"name":"MIS Quarterly Executive","vhb_2024":"B","areas":["Dienstleistung","Org","WI"]},
{"name":"MIT Sloan Management Review","vhb_2024":"B","areas":["WI"]},
{"name":"Nature Human Behaviour","vhb_2024":"A","areas":["Int. Management","Management","Marketing","Org","WI"]},
{"name":"Nature Machine Intelligence","vhb_2024":"A","areas":["WI"]},
{"name":"Omega","vhb_2024":"B","areas":["Dienstleistung","Int. Management","Logistik","Management","Nachhaltigkeit","OR","Produktion","TIE","WI"]},
{"name":"Operations Research","vhb_2024":"A+","areas":["Logistik","OR","WI"]},
{"name":"Operations Research Letters","vhb_2024":"B","areas":["OR","WI"]},
{"name":"OR Spectrum","vhb_2024":"A","areas":["Logistik","OR","Produktion","WI"]},
{"name":"Organization Science","vhb_2024":"A+","areas":["WI"]},
{"name":"Production and Operations Management","vhb_2024":"A","areas":["WI"]},
{"name":"Scandinavian Journal of Information Systems","vhb_2024":"B","areas":["Dienstleistung","WI"]},
{"name":"Service Science","vhb_2024":"B","areas":["Dienstleistung","Logistik","OR","WI"]},
{"name":"SIAM Journal on Computing","vhb_2024":"A","areas":["OR","WI"]},
{"name":"Software and Systems Modeling","vhb_2024":"B","areas":["WI"]},
{"name":"Technological Forecasting and Social Change","vhb_2024":"B","areas":["WI"]},
{"name":"Technovation","vhb_2024":"B","areas":["WI"]},
{"name":"Transportation Science","vhb_2024":"A","areas":["Logistik","OR","WI"]}
]
